html5svg2/__init__.py
html5svg2/prg.py
html5svg2/utl.py
html5svg2-0.1.4.dist-info/METADATA
html5svg2-0.1.4.dist-info/WHEEL
html5svg2-0.1.4.dist-info/licenses/LICENSE
html5svg2-0.1.4.dist-info/RECORD
