Metadata-Version: 2.1
Name: html5svg2
Version: 0.1.4
Summary: Generador de reportes en formato HTML y SVG
Project-URL: Homepage, https://github.com/borsifelix/html5svg2
Project-URL: Bug Tracker, https://github.com/borsifelix/html5svg2/releases
Author: Borsi Romero
License:                     GNU GENERAL PUBLIC LICENSE
License-File: LICENSE
Classifier: License :: OSI Approved :: MIT License
Classifier: Operating System :: OS Independent
Classifier: Programming Language :: Python :: 3
Requires-Python: >=3.3
